cain4u/__init__.py
cain4u/courses.py
cain4u/utils.py
Cain4u-0.1.0.dist-info/METADATA
Cain4u-0.1.0.dist-info/WHEEL
Cain4u-0.1.0.dist-info/top_level.txt
Cain4u-0.1.0.dist-info/RECORD
