Metadata-Version: 2.1
Name: Cain4u
Version: 0.1.0
Home-page: https://hack4u.io/
Author: Cain th
